{
  "project_info": {
    "project_number": "225282680640",
    "project_id": "examen2login",
    "storage_bucket": "examen2login.appspot.com"
  },
  "client": [
    {
      "client_info": {
        "mobilesdk_app_id": "1:225282680640:android:663dcc2e12a5df5e227ca5",
        "android_client_info": {
          "package_name": "com.example.firebaseauthentication"
        }
      },
      "oauth_client": [],
      "api_key": [
        {
          "current_key": "AIzaSyCnx3soG6JMJ7rIaEE0VpUxtTxtDjjXNY4"
        }
      ],
      "services": {
        "appinvite_service": {
          "other_platform_oauth_client": []
        }
      }
    }
  ],
  "configuration_version": "1"
}